attention_sinks/__init__.py
attention_sinks/attention_sink_kv_cache.py
attention_sinks/inject_mixin.py
attention_sinks/generation/utils.py
attention_sinks/models/__init__.py
attention_sinks/models/auto/__init__.py
attention_sinks/models/auto/modeling_auto.py
attention_sinks/models/falcon/__init__.py
attention_sinks/models/falcon/modeling_falcon.py
attention_sinks/models/falcon/pos_shift.py
attention_sinks/models/gpt_neox/__init__.py
attention_sinks/models/gpt_neox/modeling_gpt_neox.py
attention_sinks/models/gpt_neox/pos_shift.py
attention_sinks/models/gptj/__init__.py
attention_sinks/models/gptj/modeling_gptj.py
attention_sinks/models/gptj/pos_shift.py
attention_sinks/models/llama/__init__.py
attention_sinks/models/llama/modeling_llama.py
attention_sinks/models/llama/pos_shift.py
attention_sinks/models/mistral/__init__.py
attention_sinks/models/mistral/modeling_mistral.py
attention_sinks/models/mistral/pos_shift.py
attention_sinks/models/mpt/__init__.py
attention_sinks/models/mpt/modeling_mpt.py
attention_sinks/models/qwen/__init__.py
attention_sinks/models/qwen/pos_shift.py
attention_sinks/models/stablelm_epoch/__init__.py
attention_sinks/models/stablelm_epoch/pos_shift.py
attention_sinks/models/yi/__init__.py
attention_sinks/models/yi/pos_shift.py
attention_sinks-0.4.0.dist-info/LICENSE
attention_sinks-0.4.0.dist-info/METADATA
attention_sinks-0.4.0.dist-info/WHEEL
attention_sinks-0.4.0.dist-info/top_level.txt
attention_sinks-0.4.0.dist-info/RECORD
