Metadata-Version: 2.1
Name: attention-sinks
Version: 0.4.0
Summary: Extend LLMs to infinite length without sacrificing efficiency and performance, without retraining
Author: Tom Aarsen
Maintainer: Tom Aarsen
License: Apache-2.0
Project-URL: Repository, https://github.com/tomaarsen/attention_sinks
Keywords: data-science,natural-language-processing,artificial-intelligence,mlops,nlp,machine-learning,transformers
Requires-Python: >=3.8
License-File: LICENSE
Requires-Dist: torch
Requires-Dist: transformers ==4.34.0
Requires-Dist: tokenizers <0.15,>=0.14
Provides-Extra: dev
Requires-Dist: pre-commit ; extra == 'dev'
Requires-Dist: ruff ; extra == 'dev'
Requires-Dist: black ; extra == 'dev'
Requires-Dist: pytest ; extra == 'dev'
Requires-Dist: pytest-cov ; extra == 'dev'
Requires-Dist: spacy ; extra == 'dev'
